[
    {
        "owner": "IO",
        "baseClass": "economy",
        "priority": 1,
        "tariffCodePattern": "^(\\w*(LT))\\w*$",
        "parameters": [
            {
                "code": "description",
                "shortDescription": {
                    "ru": "Лайт",
                    "en": "Light"
                },
                "fullDescription": {
                    "ru": "",
                    "en": ""
                },
                "needToPay": null
            },
            {
                "code": "carryOn",
                "shortDescription": {
                    "ru": "1 место до 5 кг",
                    "en": "1 item up to 5 kg"
                },
                "fullDescription": {
                    "ru": "1 место до 5 кг — входит в норму провоза багажа для всех перевозок, за исключением рейсов на воздушных судах типа RRJ-95 (СУ9)",
                    "en": "1 item up to 5 kg is included in baggage allowance for all flights except flights provided with RRJ-95 (SU9) aircrafts"
                },
                "needToPay": "free"
            },
            {
                "code": "baggage",
                "shortDescription": {
                    "ru": "1 место до 20 кг",
                    "en": "1 item up to 20 kg"
                },
                "fullDescription": {
                    "ru": "",
                    "en": ""
                },
                "needToPay": "free"
            },
            {
                "code": "refundable",
                "shortDescription": {
                    "ru": "Возврат билета",
                    "en": "Refund"
                },
                "fullDescription": {
                    "ru": "Тариф полностью невозвратный",
                    "en": "Non-refundable"
                },
                "needToPay": "notAvailable"
            },
            {
                "code": "exchangeable",
                "shortDescription": {
                    "ru": "Обмен билета",
                    "en": "Exchange"
                },
                "fullDescription": {
                    "ru": "Обмен билета не разрешен",
                    "en": "Non-exchangeable"
                },
                "needToPay": "notAvailable"
            }
        ]
    },
    {
        "owner": "IO",
        "baseClass": "economy",
        "priority": 2,
        "tariffCodePattern": "^(\\w*(ST))\\w*$",
        "parameters": [
            {
                "code": "description",
                "shortDescription": {
                    "ru": "Стандарт",
                    "en": "Standard"
                },
                "fullDescription": {
                    "ru": "",
                    "en": ""
                },
                "needToPay": null
            },
            {
                "code": "carryOn",
                "shortDescription": {
                    "ru": "1 место до 5 кг",
                    "en": "1 item up to 5 kg"
                },
                "fullDescription": {
                    "ru": "1 место до 5 кг — входит в норму провоза багажа для всех перевозок, за исключением рейсов на воздушных судах типа RRJ-95 (СУ9)",
                    "en": "1 item up to 5 kg is included in baggage allowance for all flights except flights provided with RRJ-95 (SU9) aircrafts"
                },
                "needToPay": "free"
            },
            {
                "code": "baggage",
                "shortDescription": {
                    "ru": "1 место до 20 кг",
                    "en": "1 item up to 20 kg"
                },
                "fullDescription": {
                    "ru": "",
                    "en": ""
                },
                "needToPay": "free"
            },
            {
                "code": "refundable",
                "shortDescription": {
                    "ru": "Возврат билета",
                    "en": "Refund"
                },
                "fullDescription": {
                    "ru": "Возврат билета до вылета разрешен со штрафом. Возврат билета после вылета не разрешен",
                    "en": "Refundable before departure. A fee applies. Non-refundable after departure"
                },
                "needToPay": "charge"
            },
            {
                "code": "exchangeable",
                "shortDescription": {
                    "ru": "Обмен билета",
                    "en": "Exchange"
                },
                "fullDescription": {
                    "ru": "Обмен билета разрешен со штрафом",
                    "en": "Exchangeable. A fee applies"
                },
                "needToPay": "charge"
            }
        ]
    },
    {
        "owner": "IO",
        "baseClass": "economy",
        "priority": 3,
        "tariffCodePattern": "^(\\w*(FLEX))\\w*$",
        "parameters": [
            {
                "code": "description",
                "shortDescription": {
                    "ru": "Оптимальный+",
                    "en": "Optimal+"
                },
                "fullDescription": {
                    "ru": "",
                    "en": ""
                },
                "needToPay": null
            },
            {
                "code": "carryOn",
                "shortDescription": {
                    "ru": "1 место до 5 кг",
                    "en": "1 item up to 5 kg"
                },
                "fullDescription": {
                    "ru": "1 место до 5 кг — входит в норму провоза багажа для всех перевозок, за исключением рейсов на воздушных судах типа RRJ-95 (СУ9)",
                    "en": "1 item up to 5 kg is included in baggage allowance for all flights except flights provided with RRJ-95 (SU9) aircrafts"
                },
                "needToPay": "free"
            },
            {
                "code": "baggage",
                "shortDescription": {
                    "ru": "1 место до 20 кг",
                    "en": "1 item up to 20 kg"
                },
                "fullDescription": {
                    "ru": "",
                    "en": ""
                },
                "needToPay": "free"
            },
            {
                "code": "refundable",
                "shortDescription": {
                    "ru": "Возврат билета",
                    "en": "Refund"
                },
                "fullDescription": {
                    "ru": "Возврат билета разрешен со штрафом",
                    "en": "Refundable. A fee applies"
                },
                "needToPay": "charge"
            },
            {
                "code": "exchangeable",
                "shortDescription": {
                    "ru": "Обмен билета",
                    "en": "Exchange"
                },
                "fullDescription": {
                    "ru": "Обмен билета разрешен со штрафом",
                    "en": "Exchangeable. A fee applies"
                },
                "needToPay": "charge"
            }
        ]
    },
    {
        "owner": "IO",
        "baseClass": "business",
        "priority": 5,
        "tariffCodePattern": "^[CD]\\w*$",
        "parameters": [
            {
                "code": "description",
                "shortDescription": {
                    "ru": "Бизнес",
                    "en": "Business"
                },
                "fullDescription": {
                    "ru": "",
                    "en": ""
                },
                "needToPay": null
            },
            {
                "code": "carryOn",
                "shortDescription": {
                    "ru": "1 место до 10 кг",
                    "en": "1 item up to 10 kg"
                },
                "fullDescription": {
                    "ru": "",
                    "en": ""
                },
                "needToPay": "free"
            },
            {
                "code": "baggage",
                "shortDescription": {
                    "ru": "1 место до 30 кг",
                    "en": "1 item up to 30 kg"
                },
                "fullDescription": {
                    "ru": "1 место до 30 кг для Бизнес-класса. 1 место до 60 кг для подкласса D",
                    "en": "1 item up to 30 kg — Business class. 1 item up to 60 kg — subclass D"
                },
                "needToPay": "free"
            },
            {
                "code": "refundable",
                "shortDescription": {
                    "ru": "Возврат билета",
                    "en": "Refund"
                },
                "fullDescription": {
                    "ru": "Возврат билета разрешен со штрафом",
                    "en": "Refundable. A fee applies"
                },
                "needToPay": "charge"
            },
            {
                "code": "exchangeable",
                "shortDescription": {
                    "ru": "Обмен билета",
                    "en": "Exchange"
                },
                "fullDescription": {
                    "ru": "Обмен билета разрешен со штрафом",
                    "en": "Exchangeable. A fee applies"
                },
                "needToPay": "charge"
            }
        ]
    }
]