[
    {
        "owner": "IO",
        "baseClass": "economy",
        "priority": 1,
        "tariffCodePattern": "^(\\w*(LT))\\w*$",
        "parameters": [
            {
                "code": "description",
                "shortDescription": {
                    "ru": "Лайт",
                    "en": "Light"
                },
                "fullDescription": {
                    "ru": "",
                    "en": ""
                },
                "needToPay": null
            },
            {
                "code": "carryOn",
                "shortDescription": {
                    "ru": "1 место до 5 кг",
                    "en": "1 item up to 5 kg"
                },
                "fullDescription": {
                    "ru": "На воздушных судах Ан-24, Ан-26: 1 место ручной клади до 5 кг. На воздушных судах Superjet 100, СRJ, A-319: 1 место ручной клади до 10 кг",
                    "en": "For all flights provided with An-24, An-26 aircrafts: 1 item up to 5 kg of carry-on. For all flights provided with Superjet 100, СRJ, A-319 aircrafts: 1 item up to 10 kg of carry-on"
                },
                "needToPay": "free"
            },
            {
                "code": "baggage",
                "shortDescription": {
                    "ru": "Платный",
                    "en": "No free baggage allowance"
                },
                "fullDescription": {
                    "ru": "На воздушных судах Ан-24, Ан-26: 1 место до 15 кг багажа. На воздушных судах Superjet 100, СRJ, A-319 бесплатный провоз зарегистрированного багажа не предоставляется",
                    "en": "For all flights provided with An-24, An-26 aircrafts: 1 item up to 15 kg of checked baggage. For all flights provided with Superjet 100, СRJ, A-319 aircrafts: no free baggage allowance"
                },
                "needToPay": "charge"
            },
            {
                "code": "refundable",
                "shortDescription": {
                    "ru": "Возврат билета",
                    "en": "Refund"
                },
                "fullDescription": {
                    "ru": "Тариф полностью невозвратный",
                    "en": "Non-refundable"
                },
                "needToPay": "notAvailable"
            },
            {
                "code": "exchangeable",
                "shortDescription": {
                    "ru": "Обмен билета",
                    "en": "Exchange"
                },
                "fullDescription": {
                    "ru": "Обмен билета не разрешен",
                    "en": "Non-exchangeable"
                },
                "needToPay": "notAvailable"
            }
        ]
    },
    {
        "owner": "IO",
        "baseClass": "economy",
        "priority": 2,
        "tariffCodePattern": "^(\\w*(ST))\\w*$",
        "parameters": [
            {
                "code": "description",
                "shortDescription": {
                    "ru": "Стандарт",
                    "en": "Standard"
                },
                "fullDescription": {
                    "ru": "",
                    "en": ""
                },
                "needToPay": null
            },
            {
                "code": "carryOn",
                "shortDescription": {
                    "ru": "1 место до 5 кг",
                    "en": "1 item up to 5 kg"
                },
                "fullDescription": {
                    "ru": "",
                    "en": ""
                },
                "needToPay": "free"
            },
            {
                "code": "baggage",
                "shortDescription": {
                    "ru": "1 место до 15 кг",
                    "en": "1 item up to 15 kg"
                },
                "fullDescription": {
                    "ru": "На воздушных судах Ан-24, Ан-26: 1 место до 15 кг багажа. На воздушных судах SSJ-100, CRJ-200, A-319: 1 место до 20 кг багажа",
                    "en": "For all flights provided with An-24, An-26 aircrafts: 1 item up to 15 kg of checked baggage. For all flights provided with SSJ-100, CRJ-200, A-319 aircrafts: 1 item up to 20 kg of checked baggage"
                },
                "needToPay": "free"
            },
            {
                "code": "refundable",
                "shortDescription": {
                    "ru": "Возврат билета",
                    "en": "Refund"
                },
                "fullDescription": {
                    "ru": "Возврат билета до вылета разрешен со штрафом. Возврат билета после вылета не разрешен",
                    "en": "Refundable before departure with a fee. Non-refundable after departure"
                },
                "needToPay": "charge"
            },
            {
                "code": "exchangeable",
                "shortDescription": {
                    "ru": "Обмен билета",
                    "en": "Exchange"
                },
                "fullDescription": {
                    "ru": "Обмен билета до вылета разрешен со штрафом. Обмен билета после вылета не разрешен",
                    "en": "Exchangeable before departure with a fee. Non-exchangeable after departure"
                },
                "needToPay": "charge"
            }
        ]
    },
    {
        "owner": "IO",
        "baseClass": "economy",
        "priority": 3,
        "tariffCodePattern": "^(\\w*(FLEX))\\w*$",
        "parameters": [
            {
                "code": "description",
                "shortDescription": {
                    "ru": "Оптимальный+",
                    "en": "Optimal+"
                },
                "fullDescription": {
                    "ru": "",
                    "en": ""
                },
                "needToPay": null
            },
            {
                "code": "carryOn",
                "shortDescription": {
                    "ru": "1 место до 5 кг",
                    "en": "1 item up to 5 kg"
                },
                "fullDescription": {
                    "ru": "",
                    "en": ""
                },
                "needToPay": "free"
            },
            {
                "code": "baggage",
                "shortDescription": {
                    "ru": "1 место до 15 кг",
                    "en": "1 item up to 15 kg"
                },
                "fullDescription": {
                    "ru": "На воздушных судах Ан-24, Ан-26: 1 место до 15 кг багажа. На воздушных судах SSJ-100, CRJ-200, A-319: 1 место до 20 кг багажа",
                    "en": "For all flights provided with An-24, An-26 aircrafts: 1 item up to 15 kg of checked baggage. For all flights provided with SSJ-100, CRJ-200, A-319 aircrafts: 1 item up to 20 kg of checked baggage"
                },
                "needToPay": "free"
            },
            {
                "code": "refundable",
                "shortDescription": {
                    "ru": "Возврат билета",
                    "en": "Refund"
                },
                "fullDescription": {
                    "ru": "Возврат билета разрешен со штрафом",
                    "en": "Refundable with a fee"
                },
                "needToPay": "charge"
            },
            {
                "code": "exchangeable",
                "shortDescription": {
                    "ru": "Обмен билета",
                    "en": "Exchange"
                },
                "fullDescription": {
                    "ru": "Обмен билета разрешен со штрафом",
                    "en": "Exchangeable with a fee"
                },
                "needToPay": "charge"
            }
        ]
    }
]