[
    {
        "owner": "S7",
        "baseClass": "economy",
        "tariffCodePattern": "^(\\w*\\d*(FL))\\w*\\d*$",
        "parameters": [
            {
                "code": "description",
                "shortDescription": {
                    "ru": "Эконом Гибкий",
                    "en": "Economy Flex",
                    "de": "Economy Flexibel"
                },
                "fullDescription": {
                    "ru": "",
                    "en": ""
                },
                "needToPay": null
            },
            {
                "code": "miles",
                "shortDescription": {
                    "ru": "100% миль S7 Priority",
                    "en": "100% S7 Priority Miles"
                },
                "fullDescription": {
                    "ru": "",
                    "en": ""
                },
                "needToPay": "free"
            },
            {
                "code": "carryOn",
                "shortDescription": {
                    "ru": "1 место до 10 кг",
                    "en": "Up to 10 kg",
                    "de": "1 Beutel bis 10 kg"
                },
                "fullDescription": {
                    "ru": "",
                    "en": ""
                },
                "needToPay": "free"
            },
            {
                "code": "baggage",
                "shortDescription": {
                    "ru": "1 место до 23 кг",
                    "en": "1 item up to 23 kg"
                },
                "fullDescription": {
                    "ru": "",
                    "en": ""
                },
                "needToPay": "free"
            },
            {
                "code": "refundable",
                "shortDescription": {
                    "ru": "Возврат билета",
                    "en": "Refund",
                    "de": "Ticketrückerstattung"
                },
                "fullDescription": {
                    "ru": "Тариф на неиспользованных участках подлежит возврату. Такса YR, аэропортовые таксы и сборы по неиспользованным участкам подлежат возврату. Такса YQ возврату не подлежит. Взимается сбор за возврат за каждый возвращаемый участок, на котором была неявка, и сбор за возврат за каждый возвращаемый участок, на котором не было неявки. Сбор за оформление авиабилета возврату не подлежит",
                    "en": "Refundable. A fee applies"
                },
                "needToPay": "charge"
            },
            {
                "code": "seatsRegistration",
                "shortDescription": {
                    "ru": "Выбор места при регистрации",
                    "en": "Seat Selection",
                    "de": "Sitz bei der Anmeldung auswählen"
                },
                "fullDescription": {
                    "ru": "Бесплатный выбор места в салоне при регистрации на рейс.  Выбор места при покупке за дополнительную плату. Выбор места повышенной комфортности за дополнительную плату",
                    "en": "Seat selection permitted during the check-in"
                },
                "needToPay": "free"
            },
            {
                "code": "exchangeable",
                "shortDescription": {
                    "ru": "Изменения в билете до вылета",
                    "en": "Exchange Before Departure",
                    "de": "Änderungen der Fahrkarte vor Abfahrt"
                },
                "fullDescription": {
                    "ru": "Изменения разрешены без сборов до вылета. Разрешены со сбором за каждый сегмент после вылета. Разрешен обмен билета до более высокого тарифа в пределах группы Эконом Гибкий и Бизнес Гибкий, при доборе с Эконом Гибкий до Бизнес Гибкий со сбором за каждый сегмент. Возможна доплата разницы до доступного уровня тарифа на момент обмена билета",
                    "en": "Exchangeable before departure. No fee applies"
                },
                "needToPay": "free"
            },
            {
                "code": "meal",
                "shortDescription": {
                    "ru": "Закуска/горячее питание",
                    "en": "Snacks/Meals"
                },
                "fullDescription": {
                    "ru": "",
                    "en": ""
                },
                "needToPay": "free"
            }
        ]
    },
    {
        "owner": "S7",
        "baseClass": "economy",
        "tariffCodePattern": "^(\\w*\\d*(BS))\\w*\\d*$",
        "parameters": [
            {
                "code": "description",
                "shortDescription": {
                    "ru": "Эконом Базовый",
                    "en": "Economy Basic"
                },
                "fullDescription": {
                    "ru": "",
                    "en": ""
                },
                "needToPay": null
            },
            {
                "code": "carryOn",
                "shortDescription": {
                    "ru": "10 кг",
                    "en": "Up to 10 kg",
                    "de": "10 kg"
                },
                "fullDescription": {
                    "ru": "",
                    "en": ""
                },
                "needToPay": "free"
            },
            {
                "code": "refundable",
                "shortDescription": {
                    "ru": "Возврат билета - недоступен",
                    "en": "Non-refundable",
                    "de": "Ticketrückerstattung"
                },
                "fullDescription": {
                    "ru": "Тариф полностью невозвратный",
                    "en": "Non-refundable",
                    "de": "Fare ist völlig nicht rückzahlbar"
                },
                "needToPay": "notAvailable"
            },
            {
                "code": "miles",
                "shortDescription": {
                    "ru": "50% миль S7 Priority",
                    "en": "50% S7 Priority Miles"
                },
                "fullDescription": {
                    "ru": "",
                    "en": ""
                },
                "needToPay": "free"
            },
            {
                "code": "baggage",
                "shortDescription": {
                    "ru": "Платный",
                    "en": "No free baggage allowance"
                },
                "fullDescription": {
                    "ru": "Возможна оплата 1 места багажа до 23 кг, доплата за каждый сегмент",
                    "en": ""
                },
                "needToPay": "charge"
            },
            {
                "code": "exchangeable",
                "shortDescription": {
                    "ru": "Изменения в билете до вылета - платные",
                    "en": "Exchange Before Departure",
                    "de": "Änderungen der Fahrkarte vor Abfahrt"
                },
                "fullDescription": {
                    "ru": "Изменения разрешены со сбором за каждый сегмент до вылета. Разрешены со сбором за каждый сегмент после вылета. Обмен до более высокого тарифа Разрешен в пределах группы Эконом Базовый и Бизнес Базовый. Возможна доплата разницы до доступного уровня тарифа на момент обмена билета",
                    "en": "Exchangeable before departure. A fee applies"
                },
                "needToPay": "charge"
            },
            {
                "code": "meal",
                "shortDescription": {
                    "ru": "Закуска/горячее питание",
                    "en": "Snacks/Meals"
                },
                "fullDescription": {
                    "ru": "",
                    "en": ""
                },
                "needToPay": "free"
            },
            {
                "code": "seatsRegistration",
                "shortDescription": {
                    "ru": "Выбор места при регистрации - платно",
                    "en": "Seat Selection",
                    "de": "Sitz bei der Anmeldung auswählen"
                },
                "fullDescription": {
                    "ru": "",
                    "en": "Seat selection permitted during the check-in at extra charge"
                },
                "needToPay": "charge"
            }
        ]
    },
    {
        "owner": "S7",
        "baseClass": "business",
        "tariffCodePattern": "^(\\w*\\d*(FL))\\w*\\d*$",
        "parameters": [
            {
                "code": "description",
                "shortDescription": {
                    "ru": "Гибкий Бизнес",
                    "en": "Business Flex"
                },
                "fullDescription": {
                    "ru": "",
                    "en": ""
                },
                "needToPay": null
            },
            {
                "code": "exchangeable",
                "shortDescription": {
                    "ru": "Изменения в билете до вылета",
                    "en": "Exchange Before Departure",
                    "de": "Änderungen der Fahrkarte vor Abfahrt"
                },
                "fullDescription": {
                    "ru": "Изменения в билете до вылета разрешены без сборов",
                    "en": "Ticket exchange before departure is allowed free of charge"
                },
                "needToPay": "free"
            },
            {
                "code": "refundable",
                "shortDescription": {
                    "ru": "Возврат билета",
                    "en": "Refund",
                    "de": "Ticketrückerstattung"
                },
                "fullDescription": {
                    "ru": "Тариф на неиспользованных участках подлежит возврату. Такса YR, аэропортовые таксы и сборы по неиспользованным участкам подлежат возврату. Такса YQ возврату не подлежит. Сбор за оформление авиабилета возврату не подлежит",
                    "en": "Refundable. No fee applies"
                },
                "needToPay": "free"
            },
            {
                "code": "carryOn",
                "shortDescription": {
                    "ru": "2 места общим весом не более 15 кг, размер 55*40*20",
                    "en": "2 items up to 15 kg all, size 55*40*20"
                },
                "fullDescription": {
                    "ru": "",
                    "en": ""
                },
                "needToPay": "free"
            },
            {
                "code": "baggage",
                "shortDescription": {
                    "ru": "2 места по 32 кг",
                    "en": "2 items up to 32 kg each"
                },
                "fullDescription": {
                    "ru": "",
                    "en": ""
                },
                "needToPay": "free"
            },
            {
                "code": "seatsRegistration",
                "shortDescription": {
                    "ru": "Выбор места при регистрации",
                    "en": "Seat Selection",
                    "de": "Sitz bei der Anmeldung auswählen"
                },
                "fullDescription": {
                    "ru": "",
                    "en": ""
                },
                "needToPay": "free"
            },
            {
                "code": "miles",
                "shortDescription": {
                    "ru": "250% миль S7 Priority",
                    "en": "250% S7 Priority Miles"
                },
                "fullDescription": {
                    "ru": "",
                    "en": ""
                },
                "needToPay": "free"
            },
            {
                "code": "meal",
                "shortDescription": {
                    "ru": "Специальное меню и напитки",
                    "en": "Special Meals & Beverages"
                },
                "fullDescription": {
                    "ru": "",
                    "en": ""
                },
                "needToPay": "free"
            },
            {
                "code": "vipService",
                "shortDescription": {
                    "ru": "Бизнес зал",
                    "en": "Lounge Access",
                    "de": "Business Class Lounge"
                },
                "fullDescription": {
                    "ru": "С доступом в зал ожидания бизнес-класса",
                    "en": "With access to the Business Class lounge",
                    "de": "Zugang zur Business Class Lounge"
                },
                "needToPay": "free"
            }
        ]
    },
    {
        "owner": "S7",
        "baseClass": "business",
        "tariffCodePattern": "^(\\w*\\d*(BS))\\w*\\d*$",
        "parameters": [
            {
                "code": "description",
                "shortDescription": {
                    "ru": "Базовый Бизнес",
                    "en": "Business Basic"
                },
                "fullDescription": {
                    "ru": "",
                    "en": ""
                },
                "needToPay": null
            },
            {
                "code": "carryOn",
                "shortDescription": {
                    "ru": "2 места общим весом не более 15 кг, размер 55*40*20",
                    "en": "2 items up to 15 kg all, size 55*40*20"
                },
                "fullDescription": {
                    "ru": "",
                    "en": ""
                },
                "needToPay": "free"
            },
            {
                "code": "baggage",
                "shortDescription": {
                    "ru": "1 место 32 кг",
                    "en": "1 item up to 32 kg"
                },
                "fullDescription": {
                    "ru": "",
                    "en": ""
                },
                "needToPay": "free"
            },
            {
                "code": "refundable",
                "shortDescription": {
                    "ru": "Возврат билета - недоступен",
                    "en": "Refund",
                    "de": "Ticketrückerstattung"
                },
                "fullDescription": {
                    "ru": "Тариф полностью невозвратный. Такса YR возврату не подлежит. Такса YQ возврату не подлежит. Аэропортовые таксы и сборы по неиспользованным участкам подлежат возврату. Сбор за оформление авиабилета возврату не подлежит",
                    "en": "Non-refundable"
                },
                "needToPay": "notAvailable"
            },
            {
                "code": "exchangeable",
                "shortDescription": {
                    "ru": "Изменения в билете до вылета - платные",
                    "en": "Exchange Before Departure",
                    "de": "Änderungen der Fahrkarte vor Abfahrt"
                },
                "fullDescription": {
                    "ru": "Изменения разрешены со сбором за каждый сегмент до вылета. Разрешены со сбором за каждый сегмент после вылета. Возможна доплата разницы до доступного уровня тарифа на момент обмена билета",
                    "en": "Exchange before departure. A fee applies"
                },
                "needToPay": "charge"
            },
            {
                "code": "meal",
                "shortDescription": {
                    "ru": "Специальное меню и напитки",
                    "en": "Special Meals & Beverages"
                },
                "fullDescription": {
                    "ru": "",
                    "en": ""
                },
                "needToPay": "free"
            },
            {
                "code": "miles",
                "shortDescription": {
                    "ru": "150% миль S7 Priority",
                    "en": "150% S7 Priority Miles"
                },
                "fullDescription": {
                    "ru": "",
                    "en": ""
                },
                "needToPay": "free"
            },
            {
                "code": "seatsRegistration",
                "shortDescription": {
                    "ru": "Выбор места при регистрации",
                    "en": "Seat Selection",
                    "de": "Sitz bei der Anmeldung auswählen"
                },
                "fullDescription": {
                    "ru": "Бесплатный выбор места в салоне при регистрации на рейс",
                    "en": "Seat selection permitted during the check-in"
                },
                "needToPay": "free"
            },
            {
                "code": "vipService",
                "shortDescription": {
                    "ru": "Бизнес зал - недоступен",
                    "en": "Lounge Access",
                    "de": "Business Class Lounge"
                },
                "fullDescription": {
                    "ru": "Без доступа в зал ожидания бизнес-класса",
                    "en": "No free lounge access"
                },
                "needToPay": "notAvailable"
            }
        ]
    }
]