[
    {
        "owner": "UT",
        "baseClass": "economy",
        "perTicketRefundPenalty": "2000RUB",
        "perTicketExchangePenalty": "1000RUB",
        "tariffCodePattern": "^[A-LN-Z]FLEX(OW|RT|CR)$",
        "parameters": [
            {
                "code": "description",
                "shortDescription": {
                    "ru": "Гибкий эконом",
                    "en": ""
                },
                "fullDescription": {
                    "ru": "",
                    "en": ""
                },
                "needToPay": null
            },
            {
                "code": "refundable",
                "shortDescription": {
                    "ru": "Возврат билета",
                    "en": ""
                },
                "fullDescription": {
                    "ru": "Возврат билета разрешен со сборами",
                    "en": ""
                },
                "needToPay": "charge"
            },
            {
                "code": "miles",
                "shortDescription": {
                    "ru": "100% миль",
                    "en": ""
                },
                "fullDescription": {
                    "ru": "",
                    "en": ""
                },
                "needToPay": "free"
            },
            {
                "code": "carryOn",
                "shortDescription": {
                    "ru": "1 сумка до 10 кг",
                    "en": ""
                },
                "fullDescription": {
                    "ru": "",
                    "en": ""
                },
                "needToPay": "free"
            },
            {
                "code": "baggage",
                "shortDescription": {
                    "ru": "1 сумка до 23 кг",
                    "en": ""
                },
                "fullDescription": {
                    "ru": "",
                    "en": ""
                },
                "needToPay": "free"
            },
            {
                "code": "exchangeable",
                "shortDescription": {
                    "ru": "Обмен билета",
                    "en": ""
                },
                "fullDescription": {
                    "ru": "Обмен билета разрешен со сборами",
                    "en": ""
                },
                "needToPay": "charge"
            }
        ]
    },
    {
        "owner": "UT",
        "baseClass": "economy",
        "tariffCodePattern": "^[A-Z]LT(OW|RT|CR)$",
        "parameters": [
            {
                "code": "description",
                "shortDescription": {
                    "ru": "Лайт",
                    "en": ""
                },
                "fullDescription": {
                    "ru": "",
                    "en": ""
                },
                "needToPay": null
            },
            {
                "code": "baggage",
                "shortDescription": {
                    "ru": "Багаж платный",
                    "en": ""
                },
                "fullDescription": {
                    "ru": "",
                    "en": ""
                },
                "needToPay": "charge"
            },
            {
                "code": "carryOn",
                "shortDescription": {
                    "ru": "1 сумка до 10 кг",
                    "en": ""
                },
                "fullDescription": {
                    "ru": "",
                    "en": ""
                },
                "needToPay": "free"
            },
            {
                "code": "refundable",
                "shortDescription": {
                    "ru": "Возврат билета",
                    "en": ""
                },
                "fullDescription": {
                    "ru": "Тариф полностью невозвратный",
                    "en": ""
                },
                "needToPay": "notAvailable"
            },
            {
                "code": "exchangeable",
                "shortDescription": {
                    "ru": "Обмен билета",
                    "en": ""
                },
                "fullDescription": {
                    "ru": "Обмен билета не разрешен",
                    "en": ""
                },
                "needToPay": "notAvailable"
            },
            {
                "code": "miles",
                "shortDescription": {
                    "ru": "25% миль",
                    "en": ""
                },
                "fullDescription": {
                    "ru": "",
                    "en": ""
                },
                "needToPay": "free"
            }
        ]
    },
    {
        "owner": "UT",
        "baseClass": "economy",
        "perTicketExchangePenalty": "1000RUB",
        "tariffCodePattern": "^[A-Z]STD(OW|RT|CR)$",
        "parameters": [
            {
                "code": "description",
                "shortDescription": {
                    "ru": "Стандарт эконом",
                    "en": ""
                },
                "fullDescription": {
                    "ru": "",
                    "en": ""
                },
                "needToPay": null
            },
            {
                "code": "refundable",
                "shortDescription": {
                    "ru": "Возврат билета",
                    "en": ""
                },
                "fullDescription": {
                    "ru": "Тариф полностью невозвратный",
                    "en": ""
                },
                "needToPay": "notAvailable"
            },
            {
                "code": "miles",
                "shortDescription": {
                    "ru": "75% миль",
                    "en": ""
                },
                "fullDescription": {
                    "ru": "",
                    "en": ""
                },
                "needToPay": "free"
            },
            {
                "code": "carryOn",
                "shortDescription": {
                    "ru": "1 сумка до 10 кг",
                    "en": ""
                },
                "fullDescription": {
                    "ru": "",
                    "en": ""
                },
                "needToPay": "free"
            },
            {
                "code": "baggage",
                "shortDescription": {
                    "ru": "1 сумка до 23 кг",
                    "en": ""
                },
                "fullDescription": {
                    "ru": "",
                    "en": ""
                },
                "needToPay": "free"
            },
            {
                "code": "exchangeable",
                "shortDescription": {
                    "ru": "Обмен билета",
                    "en": ""
                },
                "fullDescription": {
                    "ru": "Обмен билета разрешен со сборами",
                    "en": ""
                },
                "needToPay": "charge"
            }
        ]
    },
    {
        "owner": "UT",
        "baseClass": "business",
        "perTicketRefundPenalty": "2000RUB",
        "perTicketExchangePenalty": "1000RUB",
        "tariffCodePattern": "^[ADCJ]FLEX(OW|RT|CR)$",
        "parameters": [
            {
                "code": "description",
                "shortDescription": {
                    "ru": "Бизнес",
                    "en": ""
                },
                "fullDescription": {
                    "ru": "",
                    "en": ""
                },
                "needToPay": null
            },
            {
                "code": "carryOn",
                "shortDescription": {
                    "ru": "2 сумки до 10 кг каждая",
                    "en": ""
                },
                "fullDescription": {
                    "ru": "",
                    "en": ""
                },
                "needToPay": "free"
            },
            {
                "code": "baggage",
                "shortDescription": {
                    "ru": "2 сумки до 32 кг каждая",
                    "en": ""
                },
                "fullDescription": {
                    "ru": "",
                    "en": ""
                },
                "needToPay": "free"
            },
            {
                "code": "miles",
                "shortDescription": {
                    "ru": "200% миль",
                    "en": ""
                },
                "fullDescription": {
                    "ru": "",
                    "en": ""
                },
                "needToPay": "free"
            },
            {
                "code": "exchangeable",
                "shortDescription": {
                    "ru": "Обмен билета",
                    "en": ""
                },
                "fullDescription": {
                    "ru": "Обмен билета разрешен со сборами",
                    "en": ""
                },
                "needToPay": "charge"
            },
            {
                "code": "refundable",
                "shortDescription": {
                    "ru": "Возврат билета",
                    "en": ""
                },
                "fullDescription": {
                    "ru": "Возврат билета разрешен со сборами",
                    "en": ""
                },
                "needToPay": "charge"
            },
            {
                "code": "vipService",
                "shortDescription": {
                    "ru": "Бизнес-зал",
                    "en": ""
                },
                "fullDescription": {
                    "ru": "С доступом в зал ожидания бизнес-класса",
                    "en": ""
                },
                "needToPay": "free"
            }
        ]
    },
    {
        "owner": "UT",
        "baseClass": "economy",
        "perTicketRefundPenalty": "2000RUB",
        "perTicketExchangePenalty": "1000RUB",
        "tariffCodePattern": "^[M]FLEX(OW|RT|CR)$",
        "parameters": [
            {
                "code": "description",
                "shortDescription": {
                    "ru": "Комфорт",
                    "en": ""
                },
                "fullDescription": {
                    "ru": "",
                    "en": ""
                },
                "needToPay": null
            },
            {
                "code": "carryOn",
                "shortDescription": {
                    "ru": "2 сумки до 10 кг",
                    "en": ""
                },
                "fullDescription": {
                    "ru": "",
                    "en": ""
                },
                "needToPay": "free"
            },
            {
                "code": "baggage",
                "shortDescription": {
                    "ru": "2 сумки до 32 кг каждая",
                    "en": ""
                },
                "fullDescription": {
                    "ru": "",
                    "en": ""
                },
                "needToPay": "free"
            },
            {
                "code": "exchangeable",
                "shortDescription": {
                    "ru": "Обмен билета",
                    "en": ""
                },
                "fullDescription": {
                    "ru": "Обмен билета разрешен со сборами",
                    "en": ""
                },
                "needToPay": "charge"
            },
            {
                "code": "refundable",
                "shortDescription": {
                    "ru": "Возврат билета",
                    "en": ""
                },
                "fullDescription": {
                    "ru": "Возврат билета разрешен со сборами",
                    "en": ""
                },
                "needToPay": "charge"
            },
            {
                "code": "miles",
                "shortDescription": {
                    "ru": "200% миль",
                    "en": ""
                },
                "fullDescription": {
                    "ru": "",
                    "en": ""
                },
                "needToPay": "free"
            }
        ]
    }
]